efi_monitor/__init__.py
efi_monitor/_cli.py
efi_monitor-0.0.1.dist-info/LICENSE
efi_monitor-0.0.1.dist-info/METADATA
efi_monitor-0.0.1.dist-info/WHEEL
efi_monitor-0.0.1.dist-info/entry_points.txt
efi_monitor-0.0.1.dist-info/top_level.txt
efi_monitor-0.0.1.dist-info/RECORD
