Metadata-Version: 2.1
Name: efi-monitor
Version: 0.0.1
Summary: Check for efi dump files with `efi-check` or remove efi dump files with `efi-clear`.
Home-page: https://github.com/ambauma/efi-monitor
Author: ambauma
License: MIT
Platform: UNKNOWN
Classifier: License :: OSI Approved :: MIT License
Classifier: Programming Language :: Python :: 3
Classifier: Programming Language :: Python :: 3.8
License-File: LICENSE
Provides-Extra: test
Requires-Dist: pydocstyle (>=6.1.1) ; extra == 'test'
Requires-Dist: pytest (>=7.0.1) ; extra == 'test'
Requires-Dist: pylint (>=2.12.2) ; extra == 'test'
Requires-Dist: pytest-mockito (>=0.0.4) ; extra == 'test'
Requires-Dist: pytest-cov (>=3.0.0) ; extra == 'test'
